destinelab/__init__.py
destinelab/climate_dt_dictionary.py
destinelab/de_token.py
destinelab/dedl_auth.py
destinelab/desp_auth.py
destinelab/extreme_dt_dictionary.py
destinelab-1.13.dist-info/licenses/LICENSE
destinelab-1.13.dist-info/METADATA
destinelab-1.13.dist-info/WHEEL
destinelab-1.13.dist-info/top_level.txt
destinelab-1.13.dist-info/RECORD
