Metadata-Version: 2.4
Name: destinelab
Version: 1.13
License: MIT
License-File: LICENSE
Requires-Dist: requests
Requires-Dist: lxml
Requires-Dist: PyJWT
Dynamic: description
Dynamic: description-content-type
Dynamic: license
Dynamic: license-file
Dynamic: requires-dist
